[{"place_id": 22258267, "licence": "Data \u00a9 OpenStreetMap contributors, ODbL 1.0. http://osm.org/copyright", "osm_type": "way", "osm_id": 68588701, "lat": "45.424588150000005", "lon": "-75.69356689291922", "class": "building", "type": "commercial", "place_rank": 30, "importance": 0.21360161928091015, "addresstype": "building", "name": "Senate of Canada Building", "display_name": "Senate of Canada Building, 2, Rideau Street, Byward Market, Lowertown, Rideau-Vanier, (Old) Ottawa, Eastern Ontario, Ontario, K1N 8W5, Canada", "boundingbox": ["45.4242224", "45.4249562", "-75.6942572", "-75.6928873"]}]